v_quantum_annealing/__init__.py
v_quantum_annealing/_version.py
v_quantum_annealing/cxxvqa.cp310-win_amd64.pyd
v_quantum_annealing/variable_type.py
v_quantum_annealing/__pycache__/__init__.cpython-310.opt-1.pyc
v_quantum_annealing/__pycache__/__init__.cpython-310.pyc
v_quantum_annealing/__pycache__/_version.cpython-310.opt-1.pyc
v_quantum_annealing/__pycache__/_version.cpython-310.pyc
v_quantum_annealing/__pycache__/variable_type.cpython-310.opt-1.pyc
v_quantum_annealing/__pycache__/variable_type.cpython-310.pyc
v_quantum_annealing/include/eigen3/signature_of_eigen3_matrix_library
v_quantum_annealing/include/eigen3/Eigen/Cholesky
v_quantum_annealing/include/eigen3/Eigen/CholmodSupport
v_quantum_annealing/include/eigen3/Eigen/Core
v_quantum_annealing/include/eigen3/Eigen/Dense
v_quantum_annealing/include/eigen3/Eigen/Eigen
v_quantum_annealing/include/eigen3/Eigen/Eigenvalues
v_quantum_annealing/include/eigen3/Eigen/Geometry
v_quantum_annealing/include/eigen3/Eigen/Householder
v_quantum_annealing/include/eigen3/Eigen/IterativeLinearSolvers
v_quantum_annealing/include/eigen3/Eigen/Jacobi
v_quantum_annealing/include/eigen3/Eigen/KLUSupport
v_quantum_annealing/include/eigen3/Eigen/LU
v_quantum_annealing/include/eigen3/Eigen/MetisSupport
v_quantum_annealing/include/eigen3/Eigen/OrderingMethods
v_quantum_annealing/include/eigen3/Eigen/PaStiXSupport
v_quantum_annealing/include/eigen3/Eigen/PardisoSupport
v_quantum_annealing/include/eigen3/Eigen/QR
v_quantum_annealing/include/eigen3/Eigen/QtAlignedMalloc
v_quantum_annealing/include/eigen3/Eigen/SPQRSupport
v_quantum_annealing/include/eigen3/Eigen/SVD
v_quantum_annealing/include/eigen3/Eigen/Sparse
v_quantum_annealing/include/eigen3/Eigen/SparseCholesky
v_quantum_annealing/include/eigen3/Eigen/SparseCore
v_quantum_annealing/include/eigen3/Eigen/SparseLU
v_quantum_annealing/include/eigen3/Eigen/SparseQR
v_quantum_annealing/include/eigen3/Eigen/StdDeque
v_quantum_annealing/include/eigen3/Eigen/StdList
v_quantum_annealing-0.1.2.dist-info/LICENSE
v_quantum_annealing-0.1.2.dist-info/METADATA
v_quantum_annealing-0.1.2.dist-info/WHEEL
v_quantum_annealing-0.1.2.dist-info/top_level.txt
v_quantum_annealing-0.1.2.dist-info/RECORD
