Metadata-Version: 2.1
Name: v-quantum-annealing
Version: 0.1.2
Summary: Quantum Computer Library for Everyone
Home-page: https://v-quantum-technology.com
Author: V-Quantum Jsc.
Author-email: nqthinh@v-quantum-technology.com
License: Apache 2
Project-URL: Source, https://github.com/v_quantum_annealing/v_quantum_annealing
Project-URL: Documentation, https://v_quantum_annealing.github.io/v_quantum_annealing
Project-URL: Reference, https://ref.v_quantum_annealing.org/index.html
Classifier: License :: OSI Approved :: Apache Software License
Classifier: Intended Audience :: Science/Research
Classifier: Programming Language :: Python
Classifier: Programming Language :: Python :: 3.7
Classifier: Programming Language :: Python :: 3.8
Classifier: Programming Language :: Python :: 3.9
Classifier: Programming Language :: Python :: 3.10
Classifier: Programming Language :: Python :: 3 :: Only
Classifier: Programming Language :: Python :: Implementation :: CPython
Classifier: Operating System :: Microsoft :: Windows
Classifier: Operating System :: POSIX
Classifier: Operating System :: Unix
Classifier: Operating System :: MacOS
Requires-Python: <3.11,>=3.7
License-File: LICENSE
Requires-Dist: numpy (<1.25.0,>=1.17.3)
Requires-Dist: dimod (<0.13.0)
Requires-Dist: scipy (<1.11.0,>=1.7.3)
Requires-Dist: requests (<2.29.0,>=2.28.0)
Requires-Dist: vqa-cimod (<1.5.0,>=0.0.1)
Requires-Dist: typing-extensions (>=4.2.0)
